keybump
setup.py
bin/keybump
keybump/__init__.py
keybump/bump_types.py
keybump/changelog.py
keybump/config.py
keybump/formatter.py
keybump/git_utils.py
keybump/package_utils.py
keybump/project.py
keybump/release.py
keybump/shell_utils.py
keybump/version.py
keybump.egg-info/PKG-INFO
keybump.egg-info/SOURCES.txt
keybump.egg-info/dependency_links.txt
keybump.egg-info/not-zip-safe
keybump.egg-info/requires.txt
keybump.egg-info/top_level.txt