Metadata-Version: 1.1
Name: keybump
Version: 3.0.1
Summary: manage your versioning like a boss .
Home-page: http://github.com/gregorynicholas/keybump
Author: gregorynicholas
Author-email: gn@gregorynicholas.com
License: MIT
Platform: any
Classifier: Environment :: Web Environment
Classifier: Intended Audience :: Developers
Classifier: License :: OSI Approved :: MIT License
Classifier: Operating System :: OS Independent
Classifier: Programming Language :: Python
Classifier: Programming Language :: Python :: 2.7
Classifier: Topic :: Internet :: WWW/HTTP :: Dynamic Content
Classifier: Topic :: Software Development :: Libraries :: Python Modules
